{
"id":"2188832",
"title":"奇异果网络科技 总经理 何丽丽",
"icon":"http://www.hndt.com/zt/persons/201807/12/2188832/res/LQHhiXOh.jpg",
"video":"http://www.hndt.com/zt/persons/201807/12/2188832/res/7loWB9Ih.mp4",
"channel":"电子商务领军人物",
"origin":"",
"time":"2018-07-12 17:57",
"body":"<p style=\"text-align: center;\"><br> \n <video class=\"edui-upload-video  vjs-default-skin\" style=\"max-width:620px; overflow:hidden;\" controls=\"controls\" preload=\"auto\" width=\"420\" height=\"280\" src=\"/zt/persons/201807/12/2188832/res/7loWB9Ih.mp4?1531624556512\" data-setup=\"{}\">\n  <source src=\"/zt/persons/201807/12/2188832/res/7loWB9Ih.mp4?1531624556512\" type=\"video/mp4\">\n <\/video><\/p>\n<p style=\"text-align: center;\"><strong>奇异果网络科技 总经理 何丽丽<\/strong><br><\/p>\n<p style=\"text-align: center;\"><img src=\"/zt/persons/201807/12/2188832/res/LQHhiXOh.jpg?1531824272080\" title=\"LQHhiXOh.jpg\" alt=\"xDlvg1YM..jpg.jpg\"><\/p>\n<p><strong>人物介绍：<\/strong><\/p>\n<p>何丽丽,女,汉族,1976年5月生,大学学历，现任河南奇异果网络科技有限公司总经理。<\/p>\n<p>河南奇异果网络科技有限公司是一家企业移动电商解决方案综合服务提供商，立足河南辐射全国，公司服务商家超过500家，重点服务商家累计GMV8000万以上，营业性收入约480万元。<\/p>\n<p>何丽丽女士是国家商务部、国家人力资源和社会保障部电子商务特聘专家，郑州市电子商务专家委员会专家，共青团河南省电子商务行业工作委员会委员，郑州移动互联网联盟常务理事，2013年互联网创业优秀个人，2014年度“新郑州城市精英”，2014年度“郑州市首届网络青年榜样”，2014年度“最佳营销风云人物”，有多年的互联网营销推广及电商运营经验，曾帮助多家企业制定互联网营销整体方案，并获得良好收益。<\/p>\n<p><br><\/p>\n<p><img><\/p>\n<p><br><\/p>\n<p><br><\/p>"
}